LICENSE
MANIFEST.in
README.rst
setup.py
gears_less/__init__.py
gears_less/compiler.js
gears_less/compiler.py
gears_less.egg-info/PKG-INFO
gears_less.egg-info/SOURCES.txt
gears_less.egg-info/dependency_links.txt
gears_less.egg-info/top_level.txt
gears_less/node_modules/less/.jshintrc
gears_less/node_modules/less/.npmignore
gears_less/node_modules/less/CHANGELOG.md
gears_less/node_modules/less/CONTRIBUTING.md
gears_less/node_modules/less/Gruntfile.js
gears_less/node_modules/less/LICENSE
gears_less/node_modules/less/README.md
gears_less/node_modules/less/bower.json
gears_less/node_modules/less/build.gradle
gears_less/node_modules/less/gradlew
gears_less/node_modules/less/gradlew.bat
gears_less/node_modules/less/package.json
gears_less/node_modules/less/.grunt/grunt-contrib-jasmine/jasmine-helper.js
gears_less/node_modules/less/.grunt/grunt-contrib-jasmine/jasmine-html.js
gears_less/node_modules/less/.grunt/grunt-contrib-jasmine/jasmine.css
gears_less/node_modules/less/.grunt/grunt-contrib-jasmine/jasmine.js
gears_less/node_modules/less/.grunt/grunt-contrib-jasmine/phantom-polyfill.js
gears_less/node_modules/less/.grunt/grunt-contrib-jasmine/reporter.js
gears_less/node_modules/less/.idea/.name
gears_less/node_modules/less/.idea/encodings.xml
gears_less/node_modules/less/.idea/jsLibraryMappings.xml
gears_less/node_modules/less/.idea/less.js.iml
gears_less/node_modules/less/.idea/misc.xml
gears_less/node_modules/less/.idea/modules.xml
gears_less/node_modules/less/.idea/vcs.xml
gears_less/node_modules/less/.idea/workspace.xml
gears_less/node_modules/less/.idea/inspectionProfiles/Project_Default.xml
gears_less/node_modules/less/.idea/inspectionProfiles/profiles_settings.xml
gears_less/node_modules/less/.idea/jsLinters/jshint.xml
gears_less/node_modules/less/.idea/libraries/sass_stdlib.xml
gears_less/node_modules/less/.idea/scopes/scope_settings.xml
gears_less/node_modules/less/benchmark/benchmark.less
gears_less/node_modules/less/benchmark/less-benchmark.js
gears_less/node_modules/less/bin/lessc
gears_less/node_modules/less/build/README.md
gears_less/node_modules/less/build/amd.js
